linkgenfx/__init__.py
linkgenfx/main.py
linkgenfx-0.2.1.dist-info/licenses/LICENSE
linkgenfx-0.2.1.dist-info/METADATA
linkgenfx-0.2.1.dist-info/WHEEL
linkgenfx-0.2.1.dist-info/entry_points.txt
linkgenfx-0.2.1.dist-info/top_level.txt
linkgenfx-0.2.1.dist-info/RECORD
