Metadata-Version: 2.4
Name: linkgenfx
Version: 0.2.1
Summary: A simple script to create Serveo.net reverse tunnels
Home-page: https://github.com/efxtv/linkgenfx
Author: EFXTv
Author-email: youremail@example.com
Classifier: Programming Language :: Python :: 3
Classifier: License :: OSI Approved :: MIT License
Classifier: Operating System :: OS Independent
Classifier: Environment :: Console
Classifier: Topic :: Utilities
Classifier: Topic :: Internet
Requires-Python: >=3.6
License-File: LICENSE
Dynamic: author
Dynamic: author-email
Dynamic: classifier
Dynamic: description
Dynamic: description-content-type
Dynamic: home-page
Dynamic: license-file
Dynamic: requires-python
Dynamic: summary
